huzaifaVoiceAssistant/__init__.py
huzaifaVoiceAssistant/main.py
huzaifa_voice_assistant-0.2.1.dist-info/METADATA
huzaifa_voice_assistant-0.2.1.dist-info/WHEEL
huzaifa_voice_assistant-0.2.1.dist-info/top_level.txt
huzaifa_voice_assistant-0.2.1.dist-info/RECORD
